netrecon/__init__.py
netrecon/__main__.py
netrecon/_version.py
netrecon/py.typed
netrecon-0.1.dev2.dist-info/LICENSE
netrecon-0.1.dev2.dist-info/METADATA
netrecon-0.1.dev2.dist-info/WHEEL
netrecon-0.1.dev2.dist-info/entry_points.txt
netrecon-0.1.dev2.dist-info/top_level.txt
netrecon-0.1.dev2.dist-info/RECORD
