Metadata-Version: 2.1
Name: netrecon
Version: 0.1.dev2
Summary: A rich CLI tool for network device reconnaissance.
Author-email: ReK42 <ReK42@users.noreply.github.com>
Maintainer-email: ReK42 <ReK42@users.noreply.github.com>
License: GNU GENERAL PUBLIC LICENSE
Project-URL: Repository, https://github.com/ReK42/netrecon
Project-URL: Issues, https://github.com/ReK42/netrecon/issues
Keywords: networking,routers,switches,cisco,juniper
Classifier: Development Status :: 3 - Alpha
Classifier: Environment :: Console
Classifier: Intended Audience :: Information Technology
Classifier: Intended Audience :: System Administrators
Classifier: Intended Audience :: Telecommunications Industry
Classifier: License :: OSI Approved :: GNU General Public License v3 or later (GPLv3+)
Classifier: Natural Language :: English
Classifier: Operating System :: OS Independent
Classifier: Programming Language :: Python
Classifier: Programming Language :: Python :: 3
Classifier: Programming Language :: Python :: 3 :: Only
Classifier: Programming Language :: Python :: 3.11
Classifier: Programming Language :: Python :: 3.12
Classifier: Topic :: System :: Archiving
Classifier: Topic :: System :: Networking
Classifier: Topic :: Utilities
Classifier: Typing :: Typed
Requires-Python: >=3.11
License-File: LICENSE
Requires-Dist: netmiko ==4.4.0
Requires-Dist: click ==8.1.7
Requires-Dist: rich ==13.7.1
Provides-Extra: build
Requires-Dist: setuptools ==70.3.0 ; extra == 'build'
Requires-Dist: setuptools-scm ==8.1.0 ; extra == 'build'
Requires-Dist: build ==1.2.1 ; extra == 'build'
Requires-Dist: twine ==5.1.1 ; extra == 'build'
Provides-Extra: test
Requires-Dist: black ==24.4.2 ; extra == 'test'
Requires-Dist: mypy ==1.10.1 ; extra == 'test'
Requires-Dist: ruff ==0.5.1 ; extra == 'test'
